nacos/__init__.py
nacos/client.py
nacos/commons.py
nacos/exception.py
nacos/files.py
nacos/listener.py
nacos/params.py
nacos/timer.py
nacos_python_sdk-0.2.dist-info/LICENSE.txt
nacos_python_sdk-0.2.dist-info/METADATA
nacos_python_sdk-0.2.dist-info/WHEEL
nacos_python_sdk-0.2.dist-info/top_level.txt
nacos_python_sdk-0.2.dist-info/RECORD
