Metadata-Version: 2.1
Name: nacos-python-sdk
Version: 0.2
Summary: nacos-python-sdk
Home-page: https://codeup.aliyun.com/612cb27957e7cd986dfaf21f/nacos-python-sdk
License: Apache License 2.0
Keywords: nacos,nacos-python-sdk
Classifier: Topic :: Software Development :: Libraries :: Python Modules
Classifier: Operating System :: OS Independent
Classifier: Programming Language :: Python
Classifier: Programming Language :: Python :: 3.8
License-File: LICENSE.txt
